yanggui/__init__.py
yanggui/__main__.py
yanggui/dataeditor.py
yanggui/dsrepo.py
yanggui/editablelist.py
yanggui/errorlog.py
yanggui/graphviewer.py
yanggui/southbound.py
yanggui/webview.py
yanggui/yanggui.py
yanggui-0.1.7.dist-info/LICENSE
yanggui-0.1.7.dist-info/METADATA
yanggui-0.1.7.dist-info/WHEEL
yanggui-0.1.7.dist-info/top_level.txt
yanggui-0.1.7.dist-info/RECORD
