Metadata-Version: 2.1
Name: yanggui
Version: 0.1.7
Summary: GUI tool for viewing and editing YANG instance data
Home-page: https://github.com/christian-herber/yanggui
Author: Christian Herber
Author-email: christian.hrbr@gmail.com
License: UNKNOWN
Keywords: yang,gui,data model,instance data,configuration
Platform: UNKNOWN
Classifier: Programming Language :: Python
Classifier: Programming Language :: Python :: 3
Classifier: License :: OSI Approved :: GNU Lesser General Public License v3 (LGPLv3)
Classifier: Operating System :: OS Independent
Classifier: Topic :: System :: Systems Administration
Requires-Python: >=3.8
Requires-Dist: wxPython (>=4.1)
Requires-Dist: yangson (>=1.4.9)
Requires-Dist: rstr (>=2.2)
Requires-Dist: PyPubSub (>=4)
Requires-Dist: importlib-metadata (>=4.8.1)
